{
  "$schema": "http://json-schema.org/draft-04/schema#",
  "id": "https://schema.occrp.org/generic/person.json#",
  "title": "Person",
  "plural": "People",
  "description": "A real person, alive or dead",
  "sortIndex": 100,
  "type": "object",
  "faIcon": "fa-user",
  "graph": "node",
  "oneOf": [
      {"$ref": "https://schema.occrp.org/generic/legal_person.json#"}
  ],
  "properties": {
    "jurisdiction_code": {
      "title": "Country of birth",
      "sortIndex": 90,
      "type": "string",
      "format": "country-code",
      "minLength": 2,
      "maxLength": 5
    },
    "family_name": {
      "title": "Family name",
      "sortIndex": 80,
      "description": "One or more family names",
      "type": ["string", "null"]
    },
    "given_name": {
      "title": "Given name",
      "sortIndex": 82,
      "description": "One or more primary given names",
      "type": ["string", "null"]
    },
    "additional_name": {
      "title": "Secondary given name",
      "sortIndex": 81,
      "description": "One or more secondary given names",
      "type": ["string", "null"]
    },
    "honorific_prefix": {
      "title": "Honorific prefix",
      "hidden": true,
      "description": "One or more honorifics preceding a person's name",
      "type": ["string", "null"]
    },
    "honorific_suffix": {
      "title": "Honorific suffix",
      "hidden": true,
      "description": "One or more honorifics following a person's name",
      "type": ["string", "null"]
    },
    "patronymic_name": {
      "title": "Patronymic",
      "description": "One or more patronymic names",
      "type": ["string", "null"]
    },
    "email": {
      "title": "E-Mail",
      "description": "A preferred email address",
      "type": ["string", "null"],
      "format": "email"
    },
    "gender": {
      "title": "Gender",
      "sortIndex": 78,
      "description": "A gender",
      "type": ["string", "null"]
    },
    "birth_date": {
      "title": "Birth date",
      "sortIndex": 86,
      "description": "A date of birth",
      "type": ["string", "null"],
      "format": "date"
    },
    "death_date": {
      "title": "Death date",
      "sortIndex": 84,
      "description": "A date of death",
      "type": ["string", "null"],
      "format": "date"
    },
    "image": {
      "description": "A URL of a head shot",
      "hidden": true,
      "type": ["string", "null"],
      "format": "uri"
    },
    "summary": {
      "title": "Summary",
      "sortIndex": 88,
      "description": "A one-line account of a person's life",
      "type": ["string", "null"]
    },
    "biography": {
      "title": "Biography",
      "sortIndex": 76,
      "description": "An extended account of a person's life",
      "type": ["string", "null"]
    },
    "residential_address": {
      "title": "Residential address",
      "$ref": "https://schema.occrp.org/generic/address.json#"
    },
    "other_names": {
      "description": "Alternate or former names",
      "rdfReverse": "person",
      "type": "array",
      "items": {"$ref": "https://schema.occrp.org/generic/other_name.json#"}
    },
    "marriages1": {
      "rdfReverse": "person1",
      "type": "array",
      "items": {"$ref": "https://schema.occrp.org/generic/marriage.json#"}
    },
    "marriages2": {
      "rdfReverse": "person2",
      "type": "array",
      "items": {"$ref": "https://schema.occrp.org/generic/marriage.json#"}
    },
    "parents": {
      "title": "Parents",
      "rdfReverse": "child",
      "type": "array",
      "items": {"$ref": "https://schema.occrp.org/generic/parenthood.json#"}
    },
    "children": {
      "title": "Children",
      "rdfReverse": "parent",
      "type": "array",
      "items": {"$ref": "https://schema.occrp.org/generic/parenthood.json#"}
    },
    "postal_address": {
      "title": "Postal address",
      "$ref": "https://schema.occrp.org/generic/address.json#"
    },
    "contact_details": {
      "title": "Contact details",
      "description": "Means of contacting the person",
      "type": "array",
      "items": {
        "$ref": "https://schema.occrp.org/generic/contact_detail.json#"
      }
    }
  }
}
